spicy_cli/__init__.py
spicy_cli/main.py
spicy_cli/commands/__init__.py
spicy_cli/commands/base.py
spicy_cli/commands/command1.py
spicy_cli/commands/command2.py
spicy_cli/commands/config.py
spicy_cli/commands/plugin.py
spicy_cli/commands/uuid.py
spicy_cli/config/__init__.py
spicy_cli/plugins/__init__.py
spicy_cli-0.1.0.dist-info/METADATA
spicy_cli-0.1.0.dist-info/WHEEL
spicy_cli-0.1.0.dist-info/entry_points.txt
spicy_cli-0.1.0.dist-info/licenses/LICENSE
spicy_cli-0.1.0.dist-info/RECORD
