Metadata-Version: 2.4
Name: spicy-cli
Version: 0.1.0
Summary: A Python CLI with multiple commands
Project-URL: homepage, https://spicycentral.org/
Project-URL: repository, https://github.com/darkflib/spicy-cli
Project-URL: documentation, https://darkflib.github.io/spicy-cli/
Project-URL: issue-tracker, https://github.com/darkflib/spicy-cli/issues
Project-URL: source, https://github.com/darkflib/spicy-cli
Project-URL: changelog, https://dev.spicycentral.org/spicy-cli/changelog
Project-URL: pypi, https://pypi.org/spicycentral/spicy-cli/
Author-email: Mike <darkflib@gmail.com>
License: MIT
License-File: LICENSE
Classifier: Development Status :: 3 - Alpha
Classifier: Intended Audience :: Developers
Classifier: License :: OSI Approved :: MIT License
Classifier: Operating System :: OS Independent
Classifier: Programming Language :: Python :: 3
Classifier: Programming Language :: Python :: 3.11
Classifier: Programming Language :: Python :: 3.12
Classifier: Programming Language :: Python :: 3.13
Requires-Python: >=3.11
Requires-Dist: httpx>=0.26.0
Requires-Dist: pydantic>=2.5.0
Requires-Dist: python-dotenv>=1.0.0
Requires-Dist: rich>=13.7.0
Requires-Dist: typer>=0.9.0
Provides-Extra: dev
Requires-Dist: bandit>=1.7.0; extra == 'dev'
Requires-Dist: black>=23.12.0; extra == 'dev'
Requires-Dist: isort>=5.13.0; extra == 'dev'
Requires-Dist: mypy>=1.8.0; extra == 'dev'
Requires-Dist: pre-commit>=3.6.0; extra == 'dev'
Requires-Dist: pylint>=3.0.2; extra == 'dev'
Requires-Dist: pytest-cov>=4.1.0; extra == 'dev'
Requires-Dist: pytest>=7.4.0; extra == 'dev'
Requires-Dist: ruff>=0.1.8; extra == 'dev'
Requires-Dist: safety>=2.3.0; extra == 'dev'
Requires-Dist: types-setuptools>=69.0.0; extra == 'dev'
